meursing/__init__.py
meursing/cli.py
meursing/meursing.py
meursing-0.1.0.dist-info/AUTHORS.rst
meursing-0.1.0.dist-info/LICENSE
meursing-0.1.0.dist-info/METADATA
meursing-0.1.0.dist-info/WHEEL
meursing-0.1.0.dist-info/entry_points.txt
meursing-0.1.0.dist-info/top_level.txt
meursing-0.1.0.dist-info/RECORD
