Metadata-Version: 2.1
Name: meursing
Version: 0.1.0
Summary: Meursing coder - creates customs master data for agrifood products requiring a four-digit additional code for customs and duty purposes
Home-page: https://github.com/bchcustoms/meursing
Author: Colm Halpin
Author-email: colm.halpin@bchcustoms.com
License: MIT license
Keywords: meursing
Platform: UNKNOWN
Classifier: Development Status :: 2 - Pre-Alpha
Classifier: Intended Audience :: Developers
Classifier: License :: OSI Approved :: MIT License
Classifier: Natural Language :: English
Classifier: Programming Language :: Python :: 3
Classifier: Programming Language :: Python :: 3.5
Classifier: Programming Language :: Python :: 3.6
Classifier: Programming Language :: Python :: 3.7
Classifier: Programming Language :: Python :: 3.8
Requires-Python: >=3.5
Requires-Dist: Click (>=7.0)
